dynamicio/__init__.py
dynamicio/__main__.py
dynamicio/cli.py
dynamicio/config/__init__.py
dynamicio/config/io_config.py
dynamicio/config/pydantic/__init__.py
dynamicio/config/pydantic/config.py
dynamicio/config/pydantic/io_resources.py
dynamicio/config/pydantic/table_schema.py
dynamicio/core.py
dynamicio/errors.py
dynamicio/metrics.py
dynamicio/mixins/__init__.py
dynamicio/mixins/utils.py
dynamicio/mixins/with_athena.py
dynamicio/mixins/with_kafka.py
dynamicio/mixins/with_local.py
dynamicio/mixins/with_postgres.py
dynamicio/mixins/with_s3.py
dynamicio/py.typed
dynamicio/validations.py
dynamicio-7.3.1.dist-info/LICENSE
dynamicio-7.3.1.dist-info/METADATA
dynamicio-7.3.1.dist-info/WHEEL
dynamicio-7.3.1.dist-info/entry_points.txt
dynamicio-7.3.1.dist-info/RECORD
