Metadata-Version: 2.3
Name: dynamicio
Version: 7.3.1
Summary: Panda's wrapper for IO operations
License: Apache-2.0
Keywords: data,pandas,io
Author: Christos Hadjinikolis
Author-email: christos.hadjinikolis@gmail.com
Requires-Python: >=3.10,<3.13
Classifier: License :: OSI Approved :: Apache Software License
Classifier: Programming Language :: Python :: 3
Classifier: Programming Language :: Python :: 3.10
Classifier: Programming Language :: Python :: 3.11
Classifier: Programming Language :: Python :: 3.12
Requires-Dist: PyYAML (>=5.4.1)
Requires-Dist: SQLAlchemy (>=1.4.11)
Requires-Dist: awscli (>=1.22.24)
Requires-Dist: boto3 (>=1.20.24)
Requires-Dist: confluent-kafka (>=2.4.0,<2.5.0)
Requires-Dist: fastparquet (>=0.8.0)
Requires-Dist: fsspec (==2022.11.0)
Requires-Dist: libcst (==1.5.1)
Requires-Dist: logzero (>=1.7.0)
Requires-Dist: magic-logger (>=1.0.2)
Requires-Dist: no_implicit_optional (==1.4.0)
Requires-Dist: numpy (>=1.24.0,<2.0.0)
Requires-Dist: pandas (>=1.5.1)
Requires-Dist: psycopg2-binary (>=2.9.3,<2.10.0)
Requires-Dist: pyarrow (>=10.0.1)
Requires-Dist: pyathena
Requires-Dist: pydantic (>=1.9.2,<3)
Requires-Dist: python-json-logger (>=2.0.1,<2.1.0)
Requires-Dist: s3fs (==0.4.2)
Requires-Dist: simplejson (>=3.17.2,<3.18.0)
Requires-Dist: tables (>=3.10.1)
